README.md
setup.py
biofilm/__init__.py
biofilm/_version.py
biofilm/feature_inspection.py
biofilm/feature_selection.py
biofilm/optimize.py
biofilm/plot.py
biofilm/refit.py
biofilm.egg-info/PKG-INFO
biofilm.egg-info/SOURCES.txt
biofilm.egg-info/dependency_links.txt
biofilm.egg-info/requires.txt
biofilm.egg-info/top_level.txt
biofilm/algo/feature_inspection.py
biofilm/algo/feature_selection.py
biofilm/util/__init__.py
biofilm/util/ask_logging.py
biofilm/util/data.py
biofilm/util/draw.py
biofilm/util/inspect_featurefiles.py
biofilm/util/out.py