Metadata-Version: 2.1
Name: biofilm
Version: 0.1.126
Summary: make it easy to generate a FILtering Models for BIOlogical data
Home-page: https://github.com/smautner/biofilm
Author: Stefan Mautner
Author-email: myl4stn4m3stef@gmail.com
License: GPLv3
Requires-Python: >=3.8
